uvy/__init__.py
uvy/main.py
uvy/py.typed
uvy/cli/__init__.py
uvy/cli/types.py
uvy/cli/utils.py
uvy/cli/check/__init__.py
uvy/cli/check/cycle_command.py
uvy/cli/packages/__init__.py
uvy/cli/packages/command.py
uvy/config/__init__.py
uvy/config/mappers.py
uvy/config/models.py
uvy/config/reader.py
uvy/config/uvy.py
uvy/data_printer/__init__.py
uvy/data_printer/ascii_printer.py
uvy/data_printer/base_printer.py
uvy/data_printer/factory.py
uvy/data_printer/json_printer.py
uvy/data_printer/markdown_printer.py
uvy/data_printer/text_printer.py
uvy/data_printer/types.py
uvy/data_printer/unicode_printer.py
uvy/graph/__init__.py
uvy/graph/dg.py
uvy/packages/__init__.py
uvy/packages/discovery_service.py
uvy/packages/models.py
uvy/packages/package_registry.py
uvy/packages/packages_facade.py
uvy-0.2.0.dist-info/METADATA
uvy-0.2.0.dist-info/WHEEL
uvy-0.2.0.dist-info/entry_points.txt
uvy-0.2.0.dist-info/RECORD
