Metadata-Version: 2.4
Name: uvy
Version: 0.2.0
Summary: A toolkit for uv monorepos
Requires-Python: <3.14,>=3.8
Requires-Dist: hatchling
Requires-Dist: packaging
Requires-Dist: rustworkx
Requires-Dist: tomli
